fritzchecksum/__init__.py
fritzchecksum/checksum.py
fritzchecksum/cli.py
fritzchecksum/py3.py
fritzchecksum/version.py
fritzchecksum-0.0.4.dist-info/DESCRIPTION.rst
fritzchecksum-0.0.4.dist-info/METADATA
fritzchecksum-0.0.4.dist-info/RECORD
fritzchecksum-0.0.4.dist-info/WHEEL
fritzchecksum-0.0.4.dist-info/entry_points.txt
fritzchecksum-0.0.4.dist-info/metadata.json
fritzchecksum-0.0.4.dist-info/top_level.txt
