Metadata-Version: 2.0
Name: fritzchecksum
Version: 0.0.4
Summary: AVM Fritz!Box Checksum Calculator/Overwriter
Home-page: https://github.com/mementum/fritzchecksum
Author: Daniel Rodriguez
Author-email: danjrod@gmail.com
License: GPLv3+
Download-URL: https://github.com/mementum/fritzchecksum/tarball/0.0.4
Keywords: development
Platform: UNKNOWN
Classifier: Development Status :: 5 - Production/Stable
Classifier: Intended Audience :: Developers
Classifier: Topic :: Software Development
Classifier: License :: OSI Approved :: GNU General Public License v3 or later (GPLv3+)
Classifier: Programming Language :: Python :: 2
Classifier: Programming Language :: Python :: 2.7
Classifier: Programming Language :: Python :: 3
Classifier: Programming Language :: Python :: 3.2
Classifier: Programming Language :: Python :: 3.3
Classifier: Programming Language :: Python :: 3.4
Classifier: Programming Language :: Python :: 3.5
Classifier: Operating System :: OS Independent
